mkrst/__init__.py
mkrst_themes/__init__.py
mkrst_themes/classic/fonts/LICENSE
mkrst_themes/classic/fonts/Philosopher-Bold.ttf
mkrst_themes/classic/fonts/Philosopher-BoldItalic.ttf
mkrst_themes/classic/fonts/Philosopher-Italic.ttf
mkrst_themes/classic/fonts/Philosopher-Regular.ttf
mkrst_themes/classic/html/links.html
mkrst_themes/classic/html/pygments.css
mkrst_themes/classic/html/stylesheet.css
mkrst_themes/classic/odt/stylesheet.odt
mkrst_themes/classic/pdf/stylesheet.style
mkrst_themes/classic/pdf/stylesheet.yaml
mkrst_themes/default/fonts/Cantarell-Bold.ttf
mkrst_themes/default/fonts/Cantarell-BoldOblique.ttf
mkrst_themes/default/fonts/Cantarell-Oblique.ttf
mkrst_themes/default/fonts/Cantarell-Regular.ttf
mkrst_themes/default/fonts/SIL Open Font License.txt
mkrst_themes/default/html/links.html
mkrst_themes/default/html/pygments.css
mkrst_themes/default/html/stylesheet.css
mkrst_themes/default/odt/stylesheet.odt
mkrst_themes/default/pdf/stylesheet.style
mkrst_themes/default/pdf/stylesheet.yaml
mkrst_themes/overclock/fonts/OFL.txt
mkrst_themes/overclock/fonts/Overlock-Black.ttf
mkrst_themes/overclock/fonts/Overlock-BlackItalic.ttf
mkrst_themes/overclock/fonts/Overlock-Bold.ttf
mkrst_themes/overclock/fonts/Overlock-BoldItalic.ttf
mkrst_themes/overclock/fonts/Overlock-Italic.ttf
mkrst_themes/overclock/fonts/Overlock-Regular.ttf
mkrst_themes/overclock/html/links.html
mkrst_themes/overclock/html/pygments.css
mkrst_themes/overclock/html/stylesheet.css
mkrst_themes/overclock/odt/stylesheet.odt
mkrst_themes/overclock/pdf/stylesheet.style
mkrst_themes/overclock/pdf/stylesheet.yaml
mkrst_themes/standard/fonts/FiraCode-Bold.ttf
mkrst_themes/standard/fonts/FiraCode-Medium.ttf
mkrst_themes/standard/fonts/LICENSE
mkrst_themes/standard/fonts/NotoSans-Black.ttf
mkrst_themes/standard/fonts/NotoSans-BlackItalic.ttf
mkrst_themes/standard/fonts/NotoSans-Bold.ttf
mkrst_themes/standard/fonts/NotoSans-BoldItalic.ttf
mkrst_themes/standard/fonts/NotoSans-Italic.ttf
2lazy2rest-0.2.2.dist-info/METADATA
2lazy2rest-0.2.2.dist-info/WHEEL
2lazy2rest-0.2.2.dist-info/entry_points.txt
2lazy2rest-0.2.2.dist-info/RECORD
