Metadata-Version: 2.1
Name: 2lazy2rest
Version: 0.2.2
Summary: Effortless generation of PDF, HTML & ODT documents from RST (ReStructuredText)
License: MIT
Author: fdev31
Author-email: fdev31@gmail.com
Requires-Python: >=3.8,<4.0
Classifier: License :: OSI Approved :: MIT License
Classifier: Programming Language :: Python :: 3
Classifier: Programming Language :: Python :: 3.8
Classifier: Programming Language :: Python :: 3.9
Classifier: Programming Language :: Python :: 3.10
Classifier: Programming Language :: Python :: 3.11
Requires-Dist: docutils (>=0.10)
Requires-Dist: rst2pdf (>=0.99,<0.100)
